voidlib/__init__.py
voidlib/learn/__init__.py
voidlib/learn/databuilder.py
voidlib/med/__init__.py
voidlib/med/dicom.py
voidlib-0.0.3.dist-info/METADATA
voidlib-0.0.3.dist-info/WHEEL
voidlib-0.0.3.dist-info/licenses/LICENSE
voidlib-0.0.3.dist-info/RECORD
