Metadata-Version: 2.1
Name: voidlib
Version: 0.0.3
Summary: personal library
Project-URL: Homepage, https://github.com/voidpunk/voidlib
Project-URL: Bug Tracker, https://github.com/voidpunk/voidlib/issues
Author-email: Nil <voidpunk.glitch@gmail.com>
License-File: LICENSE
Classifier: License :: OSI Approved :: GNU General Public License v3 (GPLv3)
Classifier: Operating System :: OS Independent
Classifier: Programming Language :: Python :: 3
Requires-Python: >=3.10
Requires-Dist: matplotlib>=3.7
Requires-Dist: numpy>=1.24
Requires-Dist: opencv-python>=4.7
Requires-Dist: pydicom>=2.3
